[{"fields":{"identifiant_de_l_etablissement":"0630375R","secteur_d_etablissement":"0","nom_etablissement":"Ecole élémentaire Félix Thonat","numero_telephone_uai":"473776451","adresse_1":"8 rue de l'Ecole ","adresse_2":"","code_postal":"63800","nom_commune":"Cournon-d'Auvergne","ecole_elementaire":1,"ecole_maternelle":"0","coordonnees":["3.199246546288589","45.74077465874845"],"voie_generale":"","voie_technologique":"","voie_professionnelle":"","telephone":"473776451","web":"","mail":"ce.0630375R@ac-clermont.fr","hebergement":"0","ulis":"0","lycee_des_metiers":"","apprentissage":"","segpa":"","section_arts":"","section_cinema":"","section_theatre":"","section_sport":"","section_internationale":"","section_europeenne":"","lycee_Agricole":"","lycee_militaire":"","nombre_d_eleves":"282","SIREN_SIRET":"21630124200048","date_ouverture":"1965-07-22","date_maj_ligne":"2019-09-11"}},{"fields":{"identifiant_de_l_etablissement":"0630376S","secteur_d_etablissement":"0","nom_etablissement":"Ecole élémentaire Le Stade","numero_telephone_uai":"473776470","adresse_1":"10 avenue de la Libération ","adresse_2":"","code_postal":"63800","nom_commune":"Cournon-d'Auvergne","ecole_elementaire":1,"ecole_maternelle":"0","coordonnees":["3.1938976934870453","45.737796155898245"],"voie_generale":"","voie_technologique":"","voie_professionnelle":"","telephone":"473776470","web":"","mail":"ce.0630376S@ac-clermont.fr","hebergement":"0","ulis":"1","lycee_des_metiers":"","apprentissage":"","segpa":"","section_arts":"","section_cinema":"","section_theatre":"","section_sport":"","section_internationale":"","section_europeenne":"","lycee_Agricole":"","lycee_militaire":"","nombre_d_eleves":"264","SIREN_SIRET":"21630124200089","date_ouverture":"1965-07-22","date_maj_ligne":"2019-09-11"}},{"fields":{"identifiant_de_l_etablissement":"0631387R","secteur_d_etablissement":"0","nom_etablissement":"Ecole élémentaire Léon Dhermain","numero_telephone_uai":"473776461","adresse_1":"52 avenue des Dômes ","adresse_2":"","code_postal":"63800","nom_commune":"Cournon-d'Auvergne","ecole_elementaire":1,"ecole_maternelle":"0","coordonnees":["3.2010392550684625","45.730504087967624"],"voie_generale":"","voie_technologique":"","voie_professionnelle":"","telephone":"473776461","web":"","mail":"ce.0631387R@ac-clermont.fr","hebergement":"0","ulis":"1","lycee_des_metiers":"","apprentissage":"","segpa":"","section_arts":"","section_cinema":"","section_theatre":"","section_sport":"","section_internationale":"","section_europeenne":"","lycee_Agricole":"","lycee_militaire":"","nombre_d_eleves":"317","SIREN_SIRET":"21630124200071","date_ouverture":"1971-07-12","date_maj_ligne":"2019-09-11"}},{"fields":{"identifiant_de_l_etablissement":"0631396A","secteur_d_etablissement":"0","nom_etablissement":"Ecole maternelle Henri Bournel","numero_telephone_uai":"473846961","adresse_1":"6 avenue de la Libération ","adresse_2":"","code_postal":"63800","nom_commune":"Cournon-d'Auvergne","ecole_elementaire":"1","ecole_maternelle":1,"coordonnees":["3.194580671013698","45.738195697576025"],"voie_generale":"","voie_technologique":"","voie_professionnelle":"","telephone":"473846961","web":"","mail":"ce.0631396A@ac-clermont.fr","hebergement":"0","ulis":"0","lycee_des_metiers":"","apprentissage":"","segpa":"","section_arts":"","section_cinema":"","section_theatre":"","section_sport":"","section_internationale":"","section_europeenne":"","lycee_Agricole":"","lycee_militaire":"","nombre_d_eleves":"157","SIREN_SIRET":"21630124200097","date_ouverture":"1971-09-20","date_maj_ligne":"2019-09-11"}},{"fields":{"identifiant_de_l_etablissement":"0631429L","secteur_d_etablissement":"0","nom_etablissement":"Ecole maternelle Pierre Perret","numero_telephone_uai":"473848111","adresse_1":"1 bis place de la Résistance ","adresse_2":"","code_postal":"63800","nom_commune":"Cournon-d'Auvergne","ecole_elementaire":"1","ecole_maternelle":1,"coordonnees":["3.204238265793362","45.74092241418345"],"voie_generale":"","voie_technologique":"","voie_professionnelle":"","telephone":"473848111","web":"","mail":"ce.0631429L@ac-clermont.fr","hebergement":"0","ulis":"0","lycee_des_metiers":"","apprentissage":"","segpa":"","section_arts":"","section_cinema":"","section_theatre":"","section_sport":"","section_internationale":"","section_europeenne":"","lycee_Agricole":"","lycee_militaire":"","nombre_d_eleves":"95","SIREN_SIRET":"21630124200113","date_ouverture":"1972-06-09","date_maj_ligne":"2019-09-11"}},{"fields":{"identifiant_de_l_etablissement":"0631494G","secteur_d_etablissement":"0","nom_etablissement":"Ecole maternelle Léon Dhermain","numero_telephone_uai":"473693661","adresse_1":"49 avenue du Livradois ","adresse_2":"","code_postal":"63800","nom_commune":"Cournon-d'Auvergne","ecole_elementaire":"1","ecole_maternelle":1,"coordonnees":["3.2004558479840233","45.730246686100905"],"voie_generale":"","voie_technologique":"","voie_professionnelle":"","telephone":"473693661","web":"","mail":"ce.0631494G@ac-clermont.fr","hebergement":"0","ulis":"0","lycee_des_metiers":"","apprentissage":"","segpa":"","section_arts":"","section_cinema":"","section_theatre":"","section_sport":"","section_internationale":"","section_europeenne":"","lycee_Agricole":"","lycee_militaire":"","nombre_d_eleves":"160","SIREN_SIRET":"21630124200105","date_ouverture":"1974-05-08","date_maj_ligne":"2019-09-11"}},{"fields":{"identifiant_de_l_etablissement":"0631610H","secteur_d_etablissement":"0","nom_etablissement":"Ecole élémentaire Lucie Aubrac","numero_telephone_uai":"473776480","adresse_1":"4 avenue du Général Desaix ","adresse_2":"","code_postal":"63800","nom_commune":"Cournon-d'Auvergne","ecole_elementaire":1,"ecole_maternelle":"0","coordonnees":["3.188987102405989","45.73081759242908"],"voie_generale":"","voie_technologique":"","voie_professionnelle":"","telephone":"473776480","web":"","mail":"ce.0631610H@ac-clermont.fr","hebergement":"0","ulis":"0","lycee_des_metiers":"","apprentissage":"","segpa":"","section_arts":"","section_cinema":"","section_theatre":"","section_sport":"","section_internationale":"","section_europeenne":"","lycee_Agricole":"","lycee_militaire":"","nombre_d_eleves":"177","SIREN_SIRET":"21630124200055","date_ouverture":"1978-09-01","date_maj_ligne":"2019-09-11"}},{"fields":{"identifiant_de_l_etablissement":"0631611J","secteur_d_etablissement":"0","nom_etablissement":"Ecole maternelle Lucie Aubrac","numero_telephone_uai":"473693635","adresse_1":"1 avenue FOCH ","adresse_2":"","code_postal":"63800","nom_commune":"Cournon-d'Auvergne","ecole_elementaire":"1","ecole_maternelle":1,"coordonnees":["3.1891329368353896","45.7313504377419"],"voie_generale":"","voie_technologique":"","voie_professionnelle":"","telephone":"473693635","web":"","mail":"ce.0631611J@ac-clermont.fr","hebergement":"0","ulis":"0","lycee_des_metiers":"","apprentissage":"","segpa":"","section_arts":"","section_cinema":"","section_theatre":"","section_sport":"","section_internationale":"","section_europeenne":"","lycee_Agricole":"","lycee_militaire":"","nombre_d_eleves":"103","SIREN_SIRET":"21630124200063","date_ouverture":"1978-09-01","date_maj_ligne":"2019-09-11"}},{"fields":{"identifiant_de_l_etablissement":"0631791E","secteur_d_etablissement":"0","nom_etablissement":"Ecole maternelle Henri Matisse","numero_telephone_uai":"473694776","adresse_1":"Boulevard Joliot Curie ","adresse_2":"","code_postal":"63800","nom_commune":"Cournon-d'Auvergne","ecole_elementaire":"1","ecole_maternelle":1,"coordonnees":["3.2040961615273775","45.74318830586686"],"voie_generale":"","voie_technologique":"","voie_professionnelle":"","telephone":"473694776","web":"","mail":"ce.0631791E@ac-clermont.fr","hebergement":"0","ulis":"0","lycee_des_metiers":"","apprentissage":"","segpa":"","section_arts":"","section_cinema":"","section_theatre":"","section_sport":"","section_internationale":"","section_europeenne":"","lycee_Agricole":"","lycee_militaire":"","nombre_d_eleves":"123","SIREN_SIRET":"21630124200139","date_ouverture":"1985-09-01","date_maj_ligne":"2019-09-11"}},{"fields":{"identifiant_de_l_etablissement":"0631861F","secteur_d_etablissement":"1","nom_etablissement":"Lycée René Descartes","numero_telephone_uai":"04 73 77 54 50","adresse_1":"Avenue Jules Ferry","adresse_2":"BP 40","code_postal":"63800","nom_commune":"Cournon-d'Auvergne","ecole_elementaire":"","ecole_maternelle":"","coordonnees":["3.2117632242314214","45.74467798974127"],"voie_generale":"1","voie_technologique":"1","voie_professionnelle":"0","telephone":"04 73 77 54 50","web":"","mail":"ce.0631861F@ac-clermont.fr","hebergement":"1","ulis":"0","lycee_des_metiers":"0","apprentissage":"0","segpa":"0","section_arts":"1","section_cinema":"0","section_theatre":"0","section_sport":"1","section_internationale":"0","section_europeenne":"1","lycee_Agricole":"0","lycee_militaire":"0","nombre_d_eleves":"1454","SIREN_SIRET":"19630102200014","date_ouverture":"1995-09-01","date_maj_ligne":"2019-09-11","taux_de_reussite":"97%","type_etablissement":"Lycée"}},{"fields":{"identifiant_de_l_etablissement":"0630028N","secteur_d_etablissement":"0","nom_etablissement":"Collège Le Stade","numero_telephone_uai":"04 73 84 20 50","adresse_1":"20 avenue de la Libération","adresse_2":"BP 117","code_postal":"63800","nom_commune":"Cournon-d'Auvergne","ecole_elementaire":"","ecole_maternelle":"","coordonnees":["3.1912932038757256","45.736945138670265"],"voie_generale":"0","voie_technologique":"0","voie_professionnelle":"0","telephone":"04 73 84 20 50","web":"www.clg-le-stade-cournon.ac-clermont.fr","mail":"ce.0630028N@ac-clermont.fr","hebergement":"0","ulis":"1","lycee_des_metiers":"0","apprentissage":"0","segpa":"0","section_arts":"0","section_cinema":"0","section_theatre":"0","section_sport":"1","section_internationale":"0","section_europeenne":"1","lycee_Agricole":"0","lycee_militaire":"0","nombre_d_eleves":"755","SIREN_SIRET":"19630028900010","date_ouverture":"1965-05-01","date_maj_ligne":"2019-09-11","taux_de_reussite":"93,0%","tb":"32%","b":"26%","ab":"23%","type_etablissement":"collège"}},{"fields":{"identifiant_de_l_etablissement":"0631688T","secteur_d_etablissement":"0","nom_etablissement":"Collège La Ribeyre","numero_telephone_uai":"04 73 84 44 24","adresse_1":"Boulevard Pasteur","adresse_2":"","code_postal":"63800","nom_commune":"Cournon-d'Auvergne","ecole_elementaire":"","ecole_maternelle":"","coordonnees":["3.204253084399585","45.72752759553042"],"voie_generale":"0","voie_technologique":"0","voie_professionnelle":"0","telephone":"04 73 84 44 24","web":"","mail":"ce.0631688T@ac-clermont.fr","hebergement":"0","ulis":"1","lycee_des_metiers":"0","apprentissage":"0","segpa":"1","section_arts":"0","section_cinema":"0","section_theatre":"0","section_sport":"1","section_internationale":"0","section_europeenne":"0","lycee_Agricole":"0","lycee_militaire":"0","nombre_d_eleves":"730","SIREN_SIRET":"19631688900019","date_ouverture":"1980-09-01","date_maj_ligne":"2019-09-11","taux_de_reussite":"83,7%","tb":"19%","b":"19%","ab":"24%","type_etablissement":"collège"}},{"fields":{"identifiant_de_l_etablissement":"0631012H","secteur_d_etablissement":"","nom_etablissement":"Circonscription d'inspection du 1er degré de Cournon Val d'Allier","numero_telephone_uai":"473775680","adresse_1":"1 place de la Résistance ","adresse_2":"","code_postal":"63800","nom_commune":"Cournon-d'Auvergne","ecole_elementaire":"","ecole_maternelle":"","coordonnees":["3.203995122631631","45.741249732348756"],"voie_generale":"","voie_technologique":"","voie_professionnelle":"","telephone":"473775680","web":"","mail":"ien-cournon@ac-clermont.fr","hebergement":"","ulis":"","lycee_des_metiers":"","apprentissage":"","segpa":"","section_arts":"","section_cinema":"","section_theatre":"","section_sport":"","section_internationale":"","section_europeenne":"","lycee_Agricole":"","lycee_militaire":"","nombre_d_eleves":"","SIREN_SIRET":"17630431900377","date_ouverture":"1967-03-13","date_maj_ligne":"2019-09-11"}}]