[{"fields":{"identifiant_de_l_etablissement":"0591465X","statut_public_prive":"Public","nom_etablissement":"Ecole primaire","numero_telephone_uai":"327495749","adresse_1":"5 rue Coulon ","adresse_2":"","code_postal":"59530","nom_commune":"Jolimetz","ecole_elementaire":1,"ecole_maternelle":1,"coordonnees":["3.6774591678639768","50.22817550502705"],"voie_generale":"","voie_technologique":"","voie_professionnelle":"","telephone":"327495749","web":"","mail":"ce.0591465X@ac-lille.fr","hebergement":"0","ulis":"0","lycee_des_metiers":"","apprentissage":"","segpa":"","section_arts":"","section_cinema":"","section_theatre":"","section_sport":"","section_internationale":"","section_europeenne":"","lycee_Agricole":"","lycee_militaire":"","nombre_d_eleves":"119","SIREN_SIRET":"21590325300023","date_ouverture":"1965-09-01","date_maj_ligne":"2019-09-11"}}]