[{"fields":{"identifiant_de_l_etablissement":"0221176J","secteur_d_etablissement":"0","nom_etablissement":"Ecole primaire privée Notre Dame de Lourdes","numero_telephone_uai":"296254125","adresse_1":"1 PLACE DE L'EGLISE ","adresse_2":"","code_postal":"22600","nom_commune":"La Motte","ecole_elementaire":1,"ecole_maternelle":1,"coordonnees":["-2.7326491459829625","48.236093667286696"],"voie_generale":"","voie_technologique":"","voie_professionnelle":"","telephone":"296254125","web":"","mail":"ec.0221176J@ac-rennes.fr","hebergement":"0","ulis":"0","lycee_des_metiers":"","apprentissage":"","segpa":"","section_arts":"","section_cinema":"","section_theatre":"","section_sport":"","section_internationale":"","section_europeenne":"","lycee_Agricole":"","lycee_militaire":"","nombre_d_eleves":"80","SIREN_SIRET":"77740012800016","date_ouverture":"1971-03-05","date_maj_ligne":"2019-09-11"}},{"fields":{"identifiant_de_l_etablissement":"0221487X","secteur_d_etablissement":"0","nom_etablissement":"Ecole primaire publique de La Motte","numero_telephone_uai":"296254574","adresse_1":"2 rue des Lierres ","adresse_2":"","code_postal":"22600","nom_commune":"La Motte","ecole_elementaire":1,"ecole_maternelle":1,"coordonnees":["-2.7313071455062996","48.23483090514853"],"voie_generale":"","voie_technologique":"","voie_professionnelle":"","telephone":"296254574","web":"","mail":"ce.0221487X@ac-rennes.fr","hebergement":"0","ulis":"0","lycee_des_metiers":"","apprentissage":"","segpa":"","section_arts":"","section_cinema":"","section_theatre":"","section_sport":"","section_internationale":"","section_europeenne":"","lycee_Agricole":"","lycee_militaire":"","nombre_d_eleves":"167","SIREN_SIRET":"21220155200024","date_ouverture":"1971-06-19","date_maj_ligne":"2019-09-11"}},{"fields":{"identifiant_de_l_etablissement":"0830742F","secteur_d_etablissement":"0","nom_etablissement":"Ecole primaire La Motte","numero_telephone_uai":"494702686","adresse_1":"Place de la République ","adresse_2":"","code_postal":"83920","nom_commune":"La Motte","ecole_elementaire":1,"ecole_maternelle":1,"coordonnees":["6.5360987849081145","43.49182160589409"],"voie_generale":"","voie_technologique":"","voie_professionnelle":"","telephone":"494702686","web":"","mail":"ce.0830742F@ac-nice.fr","hebergement":"0","ulis":"0","lycee_des_metiers":"","apprentissage":"","segpa":"","section_arts":"","section_cinema":"","section_theatre":"","section_sport":"","section_internationale":"","section_europeenne":"","lycee_Agricole":"","lycee_militaire":"","nombre_d_eleves":"186","SIREN_SIRET":"21830085300023","date_ouverture":"1970-05-29","date_maj_ligne":"2019-09-11"}},{"fields":{"identifiant_de_l_etablissement":"0831253L","secteur_d_etablissement":"0","nom_etablissement":"Ecole maternelle La Motte","numero_telephone_uai":"494702490","adresse_1":"Place de la République ","adresse_2":"","code_postal":"83920","nom_commune":"La Motte","ecole_elementaire":"1","ecole_maternelle":1,"coordonnees":["6.535875637576426","43.491994595935985"],"voie_generale":"","voie_technologique":"","voie_professionnelle":"","telephone":"494702490","web":"","mail":"ce.0831253L@ac-nice.fr","hebergement":"0","ulis":"0","lycee_des_metiers":"","apprentissage":"","segpa":"","section_arts":"","section_cinema":"","section_theatre":"","section_sport":"","section_internationale":"","section_europeenne":"","lycee_Agricole":"","lycee_militaire":"","nombre_d_eleves":"113","SIREN_SIRET":"21830085300031","date_ouverture":"1982-09-01","date_maj_ligne":"2019-09-11"}}]