[{"fields":{"identifiant_de_l_etablissement":"0780587P","statut_public_prive":"Public","nom_etablissement":"Ecole maternelle Jean-Baptiste Corot","numero_telephone_uai":"130526220","adresse_1":"24 rue des Ecoles Jean Baudin ","adresse_2":"","code_postal":"78114","nom_commune":"Magny-les-Hameaux","ecole_elementaire":"0","ecole_maternelle":1,"coordonnees":["2.0864499857150336","48.72466807521378"],"voie_generale":"","voie_technologique":"","voie_professionnelle":"","telephone":"130526220","web":"","mail":"ce.0780587P@ac-versailles.fr","hebergement":"0","ulis":"0","lycee_des_metiers":"","apprentissage":"","segpa":"","section_arts":"","section_cinema":"","section_theatre":"","section_sport":"","section_internationale":"","section_europeenne":"","lycee_Agricole":"","lycee_militaire":"","nombre_d_eleves":"120","SIREN_SIRET":"21780356800062","date_ouverture":"1973-04-03","date_maj_ligne":"2019-09-11"}},{"fields":{"identifiant_de_l_etablissement":"0780740F","statut_public_prive":"Public","nom_etablissement":"Ecole élémentaire André Gide","numero_telephone_uai":"130527460","adresse_1":"Avenue d'Aigrefoin ","adresse_2":"","code_postal":"78114","nom_commune":"Magny-les-Hameaux","ecole_elementaire":1,"ecole_maternelle":"0","coordonnees":["2.104749432871302","48.71791669088886"],"voie_generale":"","voie_technologique":"","voie_professionnelle":"","telephone":"130527460","web":"","mail":"ce.0780740F@ac-versailles.fr","hebergement":"0","ulis":"0","lycee_des_metiers":"","apprentissage":"","segpa":"","section_arts":"","section_cinema":"","section_theatre":"","section_sport":"","section_internationale":"","section_europeenne":"","lycee_Agricole":"","lycee_militaire":"","nombre_d_eleves":"134","SIREN_SIRET":"21780356800021","date_ouverture":"1974-07-17","date_maj_ligne":"2019-09-11"}},{"fields":{"identifiant_de_l_etablissement":"0780753V","statut_public_prive":"Public","nom_etablissement":"Ecole maternelle André Gide","numero_telephone_uai":"130529588","adresse_1":"Avenue d'Aigrefoin ","adresse_2":"","code_postal":"78114","nom_commune":"Magny-les-Hameaux","ecole_elementaire":"0","ecole_maternelle":1,"coordonnees":["2.104749432871302","48.71791669088886"],"voie_generale":"","voie_technologique":"","voie_professionnelle":"","telephone":"130529588","web":"","mail":"ce.0780753V@ac-versailles.fr","hebergement":"0","ulis":"0","lycee_des_metiers":"","apprentissage":"","segpa":"","section_arts":"","section_cinema":"","section_theatre":"","section_sport":"","section_internationale":"","section_europeenne":"","lycee_Agricole":"","lycee_militaire":"","nombre_d_eleves":"72","SIREN_SIRET":"21780356800054","date_ouverture":"1974-10-15","date_maj_ligne":"2019-09-11"}},{"fields":{"identifiant_de_l_etablissement":"0780815M","statut_public_prive":"Public","nom_etablissement":"Ecole maternelle Francis Jammes","numero_telephone_uai":"130522075","adresse_1":"34 rue de la Gerbe d'Or ","adresse_2":"","code_postal":"78114","nom_commune":"Magny-les-Hameaux","ecole_elementaire":"0","ecole_maternelle":1,"coordonnees":["2.098762704686256","48.71918487869981"],"voie_generale":"","voie_technologique":"","voie_professionnelle":"","telephone":"130522075","web":"","mail":"ce.0780815M@ac-versailles.fr","hebergement":"0","ulis":"0","lycee_des_metiers":"","apprentissage":"","segpa":"","section_arts":"","section_cinema":"","section_theatre":"","section_sport":"","section_internationale":"","section_europeenne":"","lycee_Agricole":"","lycee_militaire":"","nombre_d_eleves":"131","SIREN_SIRET":"21780356800179","date_ouverture":"1976-01-05","date_maj_ligne":"2019-09-11"}},{"fields":{"identifiant_de_l_etablissement":"0780825Y","statut_public_prive":"Public","nom_etablissement":"Ecole élémentaire Louise Weiss","numero_telephone_uai":"130524435","adresse_1":"20 rue André Hodebourg ","adresse_2":"","code_postal":"78114","nom_commune":"Magny-les-Hameaux","ecole_elementaire":1,"ecole_maternelle":"0","coordonnees":["2.096172902193435","48.71801574438741"],"voie_generale":"","voie_technologique":"","voie_professionnelle":"","telephone":"130524435","web":"","mail":"ce.0780825Y@ac-versailles.fr","hebergement":"0","ulis":"0","lycee_des_metiers":"","apprentissage":"","segpa":"","section_arts":"","section_cinema":"","section_theatre":"","section_sport":"","section_internationale":"","section_europeenne":"","lycee_Agricole":"","lycee_militaire":"","nombre_d_eleves":"284","SIREN_SIRET":"21780356800161","date_ouverture":"1976-02-24","date_maj_ligne":"2019-09-11"}},{"fields":{"identifiant_de_l_etablissement":"0781739S","statut_public_prive":"Public","nom_etablissement":"Ecole élémentaire Rosa Bonheur","numero_telephone_uai":"130437125","adresse_1":"04 rue ERNEST CHAUSSON ","adresse_2":"","code_postal":"78114","nom_commune":"Magny-les-Hameaux","ecole_elementaire":1,"ecole_maternelle":"0","coordonnees":["2.061821416068761","48.74385183573425"],"voie_generale":"","voie_technologique":"","voie_professionnelle":"","telephone":"130437125","web":"","mail":"ce.0781739S@ac-versailles.fr","hebergement":"0","ulis":"0","lycee_des_metiers":"","apprentissage":"","segpa":"","section_arts":"","section_cinema":"","section_theatre":"","section_sport":"","section_internationale":"","section_europeenne":"","lycee_Agricole":"","lycee_militaire":"","nombre_d_eleves":"32","SIREN_SIRET":"21780356800104","date_ouverture":"1965-05-01","date_maj_ligne":"2019-09-11"}},{"fields":{"identifiant_de_l_etablissement":"0781740T","statut_public_prive":"Public","nom_etablissement":"Ecole élémentaire Albert Samain","numero_telephone_uai":"130526215","adresse_1":"24 rue des Ecoles Jean Baudin ","adresse_2":"","code_postal":"78114","nom_commune":"Magny-les-Hameaux","ecole_elementaire":1,"ecole_maternelle":"0","coordonnees":["2.0864499857150336","48.72466807521378"],"voie_generale":"","voie_technologique":"","voie_professionnelle":"","telephone":"130526215","web":"","mail":"ce.0781740T@ac-versailles.fr","hebergement":"0","ulis":"0","lycee_des_metiers":"","apprentissage":"","segpa":"","section_arts":"","section_cinema":"","section_theatre":"","section_sport":"","section_internationale":"","section_europeenne":"","lycee_Agricole":"","lycee_militaire":"","nombre_d_eleves":"144","SIREN_SIRET":"21780356800070","date_ouverture":"1965-05-01","date_maj_ligne":"2019-09-11"}},{"fields":{"identifiant_de_l_etablissement":"0781922R","statut_public_prive":"Public","nom_etablissement":"Ecole maternelle Petit Prince","numero_telephone_uai":"130471509","adresse_1":"01 RUE DE L EGALITE ","adresse_2":"","code_postal":"78114","nom_commune":"Magny-les-Hameaux","ecole_elementaire":"0","ecole_maternelle":1,"coordonnees":["2.0809829147305523","48.722603154228786"],"voie_generale":"","voie_technologique":"","voie_professionnelle":"","telephone":"130471509","web":"","mail":"ce.0781922R@ac-versailles.fr","hebergement":"0","ulis":"0","lycee_des_metiers":"","apprentissage":"","segpa":"","section_arts":"","section_cinema":"","section_theatre":"","section_sport":"","section_internationale":"","section_europeenne":"","lycee_Agricole":"","lycee_militaire":"","nombre_d_eleves":"103","SIREN_SIRET":"21780356800112","date_ouverture":"1992-01-01","date_maj_ligne":"2019-09-11"}},{"fields":{"identifiant_de_l_etablissement":"0781926V","statut_public_prive":"Public","nom_etablissement":"Ecole élémentaire Saint-Exupéry","numero_telephone_uai":"130524323","adresse_1":"1 RUE DE L'EGALITE ","adresse_2":"","code_postal":"78114","nom_commune":"Magny-les-Hameaux","ecole_elementaire":1,"ecole_maternelle":"0","coordonnees":["2.0816922947763437","48.72246379749331"],"voie_generale":"","voie_technologique":"","voie_professionnelle":"","telephone":"130524323","web":"","mail":"ce.0781926V@ac-versailles.fr","hebergement":"0","ulis":"0","lycee_des_metiers":"","apprentissage":"","segpa":"","section_arts":"","section_cinema":"","section_theatre":"","section_sport":"","section_internationale":"","section_europeenne":"","lycee_Agricole":"","lycee_militaire":"","nombre_d_eleves":"163","SIREN_SIRET":"21780356800120","date_ouverture":"1991-09-01","date_maj_ligne":"2019-09-11"}},{"fields":{"identifiant_de_l_etablissement":"0781171Z","statut_public_prive":"Public","nom_etablissement":"Collège Albert Einstein","numero_telephone_uai":"01 30 52 43 28","adresse_1":"10 rue Hodebourg Cressely","adresse_2":"","code_postal":"78114","nom_commune":"Magny-les-Hameaux","ecole_elementaire":"","ecole_maternelle":"","coordonnees":["2.091781493472073","48.72102627146416"],"voie_generale":"0","voie_technologique":"0","voie_professionnelle":"0","telephone":"01 30 52 43 28","web":"www.clg-einstein-magny.ac-versailles.fr","mail":"0781171Z@ac-versailles.fr","hebergement":"0","ulis":"0","lycee_des_metiers":"0","apprentissage":"0","segpa":"0","section_arts":"0","section_cinema":"0","section_theatre":"0","section_sport":"0","section_internationale":"0","section_europeenne":"1","lycee_Agricole":"0","lycee_militaire":"0","nombre_d_eleves":"447","SIREN_SIRET":"19781171400017","date_ouverture":"1977-05-23","date_maj_ligne":"2019-09-11","taux_de_reussite":"85,6%","tb":"36%","b":"18%","ab":"15%","type_etablissement":"collège"}}]