[{"fields":{"identifiant_de_l_etablissement":"0160558V","statut_public_prive":"Public","nom_etablissement":"Ecole élémentaire publique","numero_telephone_uai":"545650515","adresse_1":"GRAND'RUE ","adresse_2":"","code_postal":"16310","nom_commune":"Montemboeuf","ecole_elementaire":1,"ecole_maternelle":"0","coordonnees":["0.5564094631414138","45.775321086065354"],"voie_generale":"","voie_technologique":"","voie_professionnelle":"","telephone":"545650515","web":"","mail":"ce.0160558V@ac-poitiers.fr","hebergement":"0","ulis":"0","lycee_des_metiers":"","apprentissage":"","segpa":"","section_arts":"","section_cinema":"","section_theatre":"","section_sport":"","section_internationale":"","section_europeenne":"","lycee_Agricole":"","lycee_militaire":"","nombre_d_eleves":"120","SIREN_SIRET":"21160225500021","date_ouverture":"1970-01-12","date_maj_ligne":"2019-09-11"}},{"fields":{"identifiant_de_l_etablissement":"0160031X","statut_public_prive":"Public","nom_etablissement":"Collège","numero_telephone_uai":"05 45 65 02 72","adresse_1":"2 Rue du Petit Mairat","adresse_2":"","code_postal":"16310","nom_commune":"Montemboeuf","ecole_elementaire":"","ecole_maternelle":"","coordonnees":["0.5586110783502198","45.77636877664518"],"voie_generale":"0","voie_technologique":"0","voie_professionnelle":"0","telephone":"05 45 65 02 72","web":"","mail":"ce.0160031x@ac-poitiers.fr","hebergement":"1","ulis":"0","lycee_des_metiers":"0","apprentissage":"0","segpa":"0","section_arts":"0","section_cinema":"0","section_theatre":"0","section_sport":"0","section_internationale":"0","section_europeenne":"0","lycee_Agricole":"0","lycee_militaire":"0","nombre_d_eleves":"141","SIREN_SIRET":"19160031100010","date_ouverture":"1965-05-01","date_maj_ligne":"2019-09-11","taux_de_reussite":"89,7%","tb":"28%","b":"12%","ab":"23%","type_etablissement":"collège"}}]