[{"fields":{"identifiant_de_l_etablissement":"0860434E","secteur_d_etablissement":"0","nom_etablissement":"Ecole primaire Nouaille Maupertuis","numero_telephone_uai":"549467892","adresse_1":"15 rue des Ecoles ","adresse_2":"","code_postal":"86340","nom_commune":"Nouaillé-Maupertuis","ecole_elementaire":1,"ecole_maternelle":1,"coordonnees":["0.41101232018242223","46.50550766935763"],"voie_generale":"","voie_technologique":"","voie_professionnelle":"","telephone":"549467892","web":"","mail":"ce.0860434E@ac-poitiers.fr","hebergement":"0","ulis":"0","lycee_des_metiers":"","apprentissage":"","segpa":"","section_arts":"","section_cinema":"","section_theatre":"","section_sport":"","section_internationale":"","section_europeenne":"","lycee_Agricole":"","lycee_militaire":"","nombre_d_eleves":"168","SIREN_SIRET":"21860180500037","date_ouverture":"1965-08-23","date_maj_ligne":"2019-09-11"}},{"fields":{"identifiant_de_l_etablissement":"0860435F","secteur_d_etablissement":"0","nom_etablissement":"Ecole maternelle Nouaille Maupertuis","numero_telephone_uai":"549550957","adresse_1":"15 rue des Ecoles ","adresse_2":"","code_postal":"86340","nom_commune":"Nouaillé-Maupertuis","ecole_elementaire":"1","ecole_maternelle":1,"coordonnees":["0.4113166116878835","46.50517220575786"],"voie_generale":"","voie_technologique":"","voie_professionnelle":"","telephone":"549550957","web":"","mail":"ce.0860435F@ac-poitiers.fr","hebergement":"0","ulis":"0","lycee_des_metiers":"","apprentissage":"","segpa":"","section_arts":"","section_cinema":"","section_theatre":"","section_sport":"","section_internationale":"","section_europeenne":"","lycee_Agricole":"","lycee_militaire":"","nombre_d_eleves":"88","SIREN_SIRET":"21860180500029","date_ouverture":"1965-08-23","date_maj_ligne":"2019-09-11"}}]