[{"fields":{"identifiant_de_l_etablissement":"0740259E","secteur_d_etablissement":"0","nom_etablissement":"ECOLE PRIMAIRE PUBLIQUE MARLIOZ PASSY","numero_telephone_uai":"450475278","adresse_1":"61 avenue des Grandes Platières ","adresse_2":"","code_postal":"74190","nom_commune":"Passy","ecole_elementaire":1,"ecole_maternelle":1,"coordonnees":["6.703727242485299","45.91812373648295"],"voie_generale":"","voie_technologique":"","voie_professionnelle":"","telephone":"450475278","web":"","mail":"ce.0740259E@ac-grenoble.fr","hebergement":"0","ulis":"0","lycee_des_metiers":"","apprentissage":"","segpa":"","section_arts":"","section_cinema":"","section_theatre":"","section_sport":"","section_internationale":"","section_europeenne":"","lycee_Agricole":"","lycee_militaire":"","nombre_d_eleves":"202","SIREN_SIRET":"21740208000139","date_ouverture":"1968-09-16","date_maj_ligne":"2019-09-11"}},{"fields":{"identifiant_de_l_etablissement":"0740622Z","secteur_d_etablissement":"0","nom_etablissement":"ECOLE PRIMAIRE PUBLIQUE L'ABBAYE PASSY","numero_telephone_uai":"450780650","adresse_1":"62 rue du Lycée LE FAYET","adresse_2":"","code_postal":"74190","nom_commune":"Passy","ecole_elementaire":1,"ecole_maternelle":1,"coordonnees":["6.7068138694950985","45.90625998455309"],"voie_generale":"","voie_technologique":"","voie_professionnelle":"","telephone":"450780650","web":"","mail":"ce.0740622Z@ac-grenoble.fr","hebergement":"0","ulis":"1","lycee_des_metiers":"","apprentissage":"","segpa":"","section_arts":"","section_cinema":"","section_theatre":"","section_sport":"","section_internationale":"","section_europeenne":"","lycee_Agricole":"","lycee_militaire":"","nombre_d_eleves":"142","SIREN_SIRET":"21740208000022","date_ouverture":"1966-10-06","date_maj_ligne":"2019-09-11"}},{"fields":{"identifiant_de_l_etablissement":"0740627E","secteur_d_etablissement":"0","nom_etablissement":"ECOLE ELEMENTAIRE PUBLIQUE CHEDDE-CENTRE PASSY","numero_telephone_uai":"450781167","adresse_1":"226 grande rue Salvador Allende ","adresse_2":"","code_postal":"74190","nom_commune":"Passy","ecole_elementaire":1,"ecole_maternelle":"0","coordonnees":["6.71587019609134","45.9230125033075"],"voie_generale":"","voie_technologique":"","voie_professionnelle":"","telephone":"450781167","web":"","mail":"ce.0740627E@ac-grenoble.fr","hebergement":"0","ulis":"1","lycee_des_metiers":"","apprentissage":"","segpa":"","section_arts":"","section_cinema":"","section_theatre":"","section_sport":"","section_internationale":"","section_europeenne":"","lycee_Agricole":"","lycee_militaire":"","nombre_d_eleves":"153","SIREN_SIRET":"21740208000071","date_ouverture":"1966-10-06","date_maj_ligne":"2019-09-11"}},{"fields":{"identifiant_de_l_etablissement":"0740628F","secteur_d_etablissement":"0","nom_etablissement":"ECOLE PRIMAIRE PUBLIQUE CHEDDE LE HAUT PASSY","numero_telephone_uai":"450783302","adresse_1":"59 rue Pierre Bosson ","adresse_2":"","code_postal":"74190","nom_commune":"Passy","ecole_elementaire":1,"ecole_maternelle":1,"coordonnees":["6.719742812477872","45.929208229368186"],"voie_generale":"","voie_technologique":"","voie_professionnelle":"","telephone":"450783302","web":"","mail":"ce.0740628F@ac-grenoble.fr","hebergement":"0","ulis":"0","lycee_des_metiers":"","apprentissage":"","segpa":"","section_arts":"","section_cinema":"","section_theatre":"","section_sport":"","section_internationale":"","section_europeenne":"","lycee_Agricole":"","lycee_militaire":"","nombre_d_eleves":"88","SIREN_SIRET":"21740208000089","date_ouverture":"1966-10-06","date_maj_ligne":"2019-09-11"}},{"fields":{"identifiant_de_l_etablissement":"0740811E","secteur_d_etablissement":"0","nom_etablissement":"ECOLE MATERNELLE PUBLIQUE CHEDDE JONCTION \tPASSY","numero_telephone_uai":"450780685","adresse_1":"137 rue Salvador Allende ","adresse_2":"","code_postal":"74190","nom_commune":"Passy","ecole_elementaire":"1","ecole_maternelle":1,"coordonnees":["6.659989112411776","45.91933362544175"],"voie_generale":"","voie_technologique":"","voie_professionnelle":"","telephone":"450780685","web":"","mail":"ce.0740811E@ac-grenoble.fr","hebergement":"0","ulis":"0","lycee_des_metiers":"","apprentissage":"","segpa":"","section_arts":"","section_cinema":"","section_theatre":"","section_sport":"","section_internationale":"","section_europeenne":"","lycee_Agricole":"","lycee_militaire":"","nombre_d_eleves":"74","SIREN_SIRET":"21740208000097","date_ouverture":"1967-10-12","date_maj_ligne":"2019-09-11"}},{"fields":{"identifiant_de_l_etablissement":"0741146U","secteur_d_etablissement":"0","nom_etablissement":"ECOLE PRIMAIRE PUBLIQUE CHEF-LIEU PASSY","numero_telephone_uai":"450780825","adresse_1":"65 avenue Henri Ducoudray ","adresse_2":"","code_postal":"74190","nom_commune":"Passy","ecole_elementaire":1,"ecole_maternelle":1,"coordonnees":["6.686361735172328","45.92372064718991"],"voie_generale":"","voie_technologique":"","voie_professionnelle":"","telephone":"450780825","web":"","mail":"ce.0741146U@ac-grenoble.fr","hebergement":"0","ulis":"0","lycee_des_metiers":"","apprentissage":"","segpa":"","section_arts":"","section_cinema":"","section_theatre":"","section_sport":"","section_internationale":"","section_europeenne":"","lycee_Agricole":"","lycee_militaire":"","nombre_d_eleves":"176","SIREN_SIRET":"21740208000121","date_ouverture":"1974-06-14","date_maj_ligne":"2019-09-11"}},{"fields":{"identifiant_de_l_etablissement":"0741147V","secteur_d_etablissement":"0","nom_etablissement":"ECOLE PRIMAIRE PUBLIQUE PLATEAU D'ASSY PASSY","numero_telephone_uai":"450588116","adresse_1":"106 rue DES CLAIRS ","adresse_2":"","code_postal":"74190","nom_commune":"Passy","ecole_elementaire":1,"ecole_maternelle":1,"coordonnees":["6.708547189124125","45.93729901091285"],"voie_generale":"","voie_technologique":"","voie_professionnelle":"","telephone":"450588116","web":"","mail":"ce.0741147V@ac-grenoble.fr","hebergement":"0","ulis":"0","lycee_des_metiers":"","apprentissage":"","segpa":"","section_arts":"","section_cinema":"","section_theatre":"","section_sport":"","section_internationale":"","section_europeenne":"","lycee_Agricole":"","lycee_militaire":"","nombre_d_eleves":"192","SIREN_SIRET":"21740208000055","date_ouverture":"1974-06-14","date_maj_ligne":"2019-09-11"}},{"fields":{"identifiant_de_l_etablissement":"0890240C","secteur_d_etablissement":"0","nom_etablissement":"Ecole primaire","numero_telephone_uai":"386872554","adresse_1":"11 grande rue ","adresse_2":"","code_postal":"89510","nom_commune":"Passy","ecole_elementaire":1,"ecole_maternelle":1,"coordonnees":["3.3032002340880076","48.110131595449424"],"voie_generale":"","voie_technologique":"","voie_professionnelle":"","telephone":"386872554","web":"","mail":"ce.0890240C@ac-dijon.fr","hebergement":"0","ulis":"0","lycee_des_metiers":"","apprentissage":"","segpa":"","section_arts":"","section_cinema":"","section_theatre":"","section_sport":"","section_internationale":"","section_europeenne":"","lycee_Agricole":"","lycee_militaire":"","nombre_d_eleves":"47","SIREN_SIRET":"21890291400025","date_ouverture":"1966-10-10","date_maj_ligne":"2019-09-11"}},{"fields":{"identifiant_de_l_etablissement":"0740027C","secteur_d_etablissement":"1","nom_etablissement":"Lycée Mont Blanc René Dayve","numero_telephone_uai":"04 50 78 14 43","adresse_1":"rue René Dayve","adresse_2":"BP 60048","code_postal":"74190","nom_commune":"Passy","ecole_elementaire":"","ecole_maternelle":"","coordonnees":["6.706554487170623","45.9072988890302"],"voie_generale":"1","voie_technologique":"1","voie_professionnelle":"0","telephone":"04 50 78 14 43","web":"lypasmtb.edres74.ac-grenoble.fr","mail":"ce.0740027C@ac-grenoble.fr","hebergement":"1","ulis":"0","lycee_des_metiers":"1","apprentissage":"1","segpa":"0","section_arts":"1","section_cinema":"0","section_theatre":"0","section_sport":"1","section_internationale":"0","section_europeenne":"1","lycee_Agricole":"0","lycee_militaire":"0","nombre_d_eleves":"1381","SIREN_SIRET":"19740027800010","date_ouverture":"1965-05-01","date_maj_ligne":"2019-09-11","taux_de_reussite":"98%","type_etablissement":"Lycée"}},{"fields":{"identifiant_de_l_etablissement":"0740263J","secteur_d_etablissement":"0","nom_etablissement":"Collège de Varens","numero_telephone_uai":"04 50 78 24 71","adresse_1":"361 avenue Paul Eluard","adresse_2":"","code_postal":"74190","nom_commune":"Passy","ecole_elementaire":"","ecole_maternelle":"","coordonnees":["6.700775231568885","45.91401950123156"],"voie_generale":"0","voie_technologique":"0","voie_professionnelle":"0","telephone":"04 50 78 24 71","web":"www.ac-grenoble.fr/college/varens.passy","mail":"Ce.0740263J@ac-grenoble.fr","hebergement":"0","ulis":"1","lycee_des_metiers":"0","apprentissage":"0","segpa":"1","section_arts":"0","section_cinema":"0","section_theatre":"0","section_sport":"1","section_internationale":"0","section_europeenne":"1","lycee_Agricole":"0","lycee_militaire":"0","nombre_d_eleves":"703","SIREN_SIRET":"19740263900011","date_ouverture":"1968-10-09","date_maj_ligne":"2019-09-11","taux_de_reussite":"89,5%","tb":"30%","b":"25%","ab":"15%","type_etablissement":"collège"}}]