[{"fields":{"identifiant_de_l_etablissement":"0760607X","statut_public_prive":"Public","nom_etablissement":"Ecole maternelle","numero_telephone_uai":"235933527","adresse_1":"Route de Dieppe ","adresse_2":"","code_postal":"76340","nom_commune":"Rieux","ecole_elementaire":"0","ecole_maternelle":1,"coordonnees":["1.5806524112912392","49.93352354394934"],"voie_generale":"","voie_technologique":"","voie_professionnelle":"","telephone":"235933527","web":"","mail":"ce.0760607X@ac-rouen.fr","hebergement":"0","ulis":"0","lycee_des_metiers":"","apprentissage":"","segpa":"","section_arts":"","section_cinema":"","section_theatre":"","section_sport":"","section_internationale":"","section_europeenne":"","lycee_Agricole":"","lycee_militaire":"","nombre_d_eleves":"26","SIREN_SIRET":"21760528600020","date_ouverture":"1966-12-05","date_maj_ligne":"2019-09-11"}},{"fields":{"identifiant_de_l_etablissement":"0560740A","statut_public_prive":"Public","nom_etablissement":"Ecole primaire publique l'Escargot Bleu","numero_telephone_uai":"299919314","adresse_1":"2 rue des Trinitaires ","adresse_2":"","code_postal":"56350","nom_commune":"Rieux","ecole_elementaire":1,"ecole_maternelle":1,"coordonnees":["-2.1065888006302202","47.59796515655037"],"voie_generale":"","voie_technologique":"","voie_professionnelle":"","telephone":"299919314","web":"","mail":"ec.0560740a@ac-rennes.fr","hebergement":"0","ulis":"0","lycee_des_metiers":"","apprentissage":"","segpa":"","section_arts":"","section_cinema":"","section_theatre":"","section_sport":"","section_internationale":"","section_europeenne":"","lycee_Agricole":"","lycee_militaire":"","nombre_d_eleves":"133","SIREN_SIRET":"21560194900021","date_ouverture":"1968-07-04","date_maj_ligne":"2019-09-11"}},{"fields":{"identifiant_de_l_etablissement":"0561158E","statut_public_prive":"Privé","nom_etablissement":"Ecole primaire privée Sainte Anne","numero_telephone_uai":"299919622","adresse_1":"Rue des Milleries ","adresse_2":"","code_postal":"56350","nom_commune":"Rieux","ecole_elementaire":1,"ecole_maternelle":1,"coordonnees":["-2.104448401514334","47.59751859714385"],"voie_generale":"","voie_technologique":"","voie_professionnelle":"","telephone":"299919622","web":"","mail":"ec.0561158E@ac-rennes.fr","hebergement":"0","ulis":"0","lycee_des_metiers":"","apprentissage":"","segpa":"","section_arts":"","section_cinema":"","section_theatre":"","section_sport":"","section_internationale":"","section_europeenne":"","lycee_Agricole":"","lycee_militaire":"","nombre_d_eleves":"143","SIREN_SIRET":"77788407300019","date_ouverture":"1971-03-24","date_maj_ligne":"2019-09-11"}},{"fields":{"identifiant_de_l_etablissement":"0601781K","statut_public_prive":"Public","nom_etablissement":"Ecole primaire Jean Carette","numero_telephone_uai":"344707270","adresse_1":"Place Jean Carette ","adresse_2":"","code_postal":"60870","nom_commune":"Rieux","ecole_elementaire":1,"ecole_maternelle":1,"coordonnees":["2.518662623813497","49.298082175737015"],"voie_generale":"","voie_technologique":"","voie_professionnelle":"","telephone":"344707270","web":"","mail":"ce.0601781K@ac-amiens.fr","hebergement":"0","ulis":"0","lycee_des_metiers":"","apprentissage":"","segpa":"","section_arts":"","section_cinema":"","section_theatre":"","section_sport":"","section_internationale":"","section_europeenne":"","lycee_Agricole":"","lycee_militaire":"","nombre_d_eleves":"162","SIREN_SIRET":"21600533000040","date_ouverture":"1984-09-06","date_maj_ligne":"2019-09-11"}}]