[{"fields":{"identifiant_de_l_etablissement":"0341084U","statut_public_prive":"Public","nom_etablissement":"Ecole primaire","numero_telephone_uai":"467965784","adresse_1":"Avenue du Cardinal de Fleury ","adresse_2":"","code_postal":"34725","nom_commune":"Saint-Félix-de-Lodez","ecole_elementaire":1,"ecole_maternelle":1,"coordonnees":["3.458676635129132","43.6635113595258"],"voie_generale":"","voie_technologique":"","voie_professionnelle":"","telephone":"467965784","web":"","mail":"ce.0341084U@ac-montpellier.fr","hebergement":"0","ulis":"0","lycee_des_metiers":"","apprentissage":"","segpa":"","section_arts":"","section_cinema":"","section_theatre":"","section_sport":"","section_internationale":"","section_europeenne":"","lycee_Agricole":"","lycee_militaire":"","nombre_d_eleves":"125","SIREN_SIRET":"21340254800027","date_ouverture":"1970-06-02","date_maj_ligne":"2019-09-11"}}]