[{"fields":{"identifiant_de_l_etablissement":"0430994X","statut_public_prive":"Public","nom_etablissement":"Ecole Elémentaire","numero_telephone_uai":"471004809","adresse_1":"Place Général de Gaulle ","adresse_2":"","code_postal":"43350","nom_commune":"Saint-Paulien","ecole_elementaire":1,"ecole_maternelle":"1","coordonnees":["3.8118754893537328","45.13315798002737"],"voie_generale":"","voie_technologique":"","voie_professionnelle":"","telephone":"471004809","web":"","mail":"ce.0430994X@ac-clermont.fr","hebergement":"0","ulis":"0","lycee_des_metiers":"","apprentissage":"","segpa":"","section_arts":"","section_cinema":"","section_theatre":"","section_sport":"","section_internationale":"","section_europeenne":"","lycee_Agricole":"","lycee_militaire":"","nombre_d_eleves":"149","SIREN_SIRET":"21430216800049","date_ouverture":"2005-09-01","date_maj_ligne":"2019-09-11"}},{"fields":{"identifiant_de_l_etablissement":"0430774H","statut_public_prive":"Privé","nom_etablissement":"Ecole élémentaire privée Saint Joseph","numero_telephone_uai":"471004867","adresse_1":"1 chemin du stade de Chomeil ","adresse_2":"","code_postal":"43350","nom_commune":"Saint-Paulien","ecole_elementaire":1,"ecole_maternelle":"1","coordonnees":["3.8141831340799026","45.136912262436496"],"voie_generale":"","voie_technologique":"","voie_professionnelle":"","telephone":"471004867","web":"","mail":"ce.0430774H@ac-clermont.fr","hebergement":"0","ulis":"0","lycee_des_metiers":"","apprentissage":"","segpa":"","section_arts":"","section_cinema":"","section_theatre":"","section_sport":"","section_internationale":"","section_europeenne":"","lycee_Agricole":"","lycee_militaire":"","nombre_d_eleves":"92","SIREN_SIRET":"77915535700014","date_ouverture":"1971-03-09","date_maj_ligne":"2019-09-11"}}]