[{"fields":{"identifiant_de_l_etablissement":"0400517V","secteur_d_etablissement":"0","nom_etablissement":"Ecole primaire","numero_telephone_uai":"558793324","adresse_1":"64 route de Hagetmau ","adresse_2":"","code_postal":"40700","nom_commune":"Sainte-Colombe","ecole_elementaire":1,"ecole_maternelle":1,"coordonnees":["-0.5579185144798131","43.68166839698047"],"voie_generale":"","voie_technologique":"","voie_professionnelle":"","telephone":"558793324","web":"","mail":"ce.0400517V@ac-bordeaux.fr","hebergement":"0","ulis":"0","lycee_des_metiers":"","apprentissage":"","segpa":"","section_arts":"","section_cinema":"","section_theatre":"","section_sport":"","section_internationale":"","section_europeenne":"","lycee_Agricole":"","lycee_militaire":"","nombre_d_eleves":"72","SIREN_SIRET":"21400252900029","date_ouverture":"1967-03-08","date_maj_ligne":"2019-09-11"}},{"fields":{"identifiant_de_l_etablissement":"0331116J","secteur_d_etablissement":"0","nom_etablissement":"Ecole maternelle","numero_telephone_uai":"557479640","adresse_1":"Rocade de Maugras ","adresse_2":"","code_postal":"33350","nom_commune":"Sainte-Colombe","ecole_elementaire":"1","ecole_maternelle":1,"coordonnees":["-0.062033469074446144","44.87948067692091"],"voie_generale":"","voie_technologique":"","voie_professionnelle":"","telephone":"557479640","web":"","mail":"ce.0331116J@ac-bordeaux.fr","hebergement":"0","ulis":"0","lycee_des_metiers":"","apprentissage":"","segpa":"","section_arts":"","section_cinema":"","section_theatre":"","section_sport":"","section_internationale":"","section_europeenne":"","lycee_Agricole":"","lycee_militaire":"","nombre_d_eleves":"45","SIREN_SIRET":"21330390200026","date_ouverture":"1965-08-10","date_maj_ligne":"2019-09-11"}},{"fields":{"identifiant_de_l_etablissement":"0693154D","secteur_d_etablissement":"0","nom_etablissement":"Ecole primaire","numero_telephone_uai":"437022316","adresse_1":"166 route Nationale ","adresse_2":"","code_postal":"69560","nom_commune":"Sainte-Colombe","ecole_elementaire":1,"ecole_maternelle":1,"coordonnees":["4.866945862888332","45.52478805324561"],"voie_generale":"","voie_technologique":"","voie_professionnelle":"","telephone":"437022316","web":"","mail":"ce.0693154D@ac-lyon.fr","hebergement":"0","ulis":"0","lycee_des_metiers":"","apprentissage":"","segpa":"","section_arts":"","section_cinema":"","section_theatre":"","section_sport":"","section_internationale":"","section_europeenne":"","lycee_Agricole":"","lycee_militaire":"","nombre_d_eleves":"134","SIREN_SIRET":"21690189200044","date_ouverture":"1984-09-01","date_maj_ligne":"2019-09-11"}},{"fields":{"identifiant_de_l_etablissement":"0761165D","secteur_d_etablissement":"0","nom_etablissement":"Ecole élémentaire","numero_telephone_uai":"235573933","adresse_1":"31 impasse de l'Ecole ","adresse_2":"","code_postal":"76460","nom_commune":"Sainte-Colombe","ecole_elementaire":1,"ecole_maternelle":"0","coordonnees":["0.7587121877069394","49.796943303736015"],"voie_generale":"","voie_technologique":"","voie_professionnelle":"","telephone":"235573933","web":"","mail":"ce.0761165D@ac-rouen.fr","hebergement":"0","ulis":"0","lycee_des_metiers":"","apprentissage":"","segpa":"","section_arts":"","section_cinema":"","section_theatre":"","section_sport":"","section_internationale":"","section_europeenne":"","lycee_Agricole":"","lycee_militaire":"","nombre_d_eleves":"15","SIREN_SIRET":"21760569000023","date_ouverture":"1966-12-19","date_maj_ligne":"2019-09-11"}},{"fields":{"identifiant_de_l_etablissement":"0771384L","secteur_d_etablissement":"0","nom_etablissement":"Ecole primaire Armand François","numero_telephone_uai":"164003509","adresse_1":"7 chemin du Marais ","adresse_2":"","code_postal":"77650","nom_commune":"Sainte-Colombe","ecole_elementaire":1,"ecole_maternelle":1,"coordonnees":["3.253218833217541","48.53007011301929"],"voie_generale":"","voie_technologique":"","voie_professionnelle":"","telephone":"164003509","web":"","mail":"ce.0771384L@ac-creteil.fr","hebergement":"0","ulis":"0","lycee_des_metiers":"","apprentissage":"","segpa":"","section_arts":"","section_cinema":"","section_theatre":"","section_sport":"","section_internationale":"","section_europeenne":"","lycee_Agricole":"","lycee_militaire":"","nombre_d_eleves":"164","SIREN_SIRET":"21770404800024","date_ouverture":"1970-06-02","date_maj_ligne":"2019-09-11"}}]