[{"fields":{"identifiant_de_l_etablissement":"0370949F","statut_public_prive":"Public","nom_etablissement":"Ecole élémentaire Jacqueline Auriol","numero_telephone_uai":"247260759","adresse_1":"9 rue des Ecoles ","adresse_2":"","code_postal":"37250","nom_commune":"Sorigny","ecole_elementaire":1,"ecole_maternelle":"0","coordonnees":["0.6945203973567187","47.238645450544695"],"voie_generale":"","voie_technologique":"","voie_professionnelle":"","telephone":"247260759","web":"","mail":"ce.0370949F@ac-orleans-tours.fr","hebergement":"0","ulis":"0","lycee_des_metiers":"","apprentissage":"","segpa":"","section_arts":"","section_cinema":"","section_theatre":"","section_sport":"","section_internationale":"","section_europeenne":"","lycee_Agricole":"","lycee_militaire":"","nombre_d_eleves":"192","SIREN_SIRET":"21370250900026","date_ouverture":"1970-05-27","date_maj_ligne":"2019-09-11"}},{"fields":{"identifiant_de_l_etablissement":"0371369M","statut_public_prive":"Public","nom_etablissement":"Ecole maternelle Pierre Petit","numero_telephone_uai":"247269765","adresse_1":"11 rue des Ecoles ","adresse_2":"","code_postal":"37250","nom_commune":"Sorigny","ecole_elementaire":"0","ecole_maternelle":1,"coordonnees":["0.6937505761428593","47.238464416905714"],"voie_generale":"","voie_technologique":"","voie_professionnelle":"","telephone":"247269765","web":"","mail":"ce.0371369M@ac-orleans-tours.fr","hebergement":"0","ulis":"0","lycee_des_metiers":"","apprentissage":"","segpa":"","section_arts":"","section_cinema":"","section_theatre":"","section_sport":"","section_internationale":"","section_europeenne":"","lycee_Agricole":"","lycee_militaire":"","nombre_d_eleves":"117","SIREN_SIRET":"21370250900034","date_ouverture":"1982-09-01","date_maj_ligne":"2019-09-11"}}]