[{"fields":{"identifiant_de_l_etablissement":"0460363V","statut_public_prive":"Public","nom_etablissement":"Ecole primaire publique","numero_telephone_uai":"565101470","adresse_1":"Lieu-dit Las Garoles ","adresse_2":"","code_postal":"46500","nom_commune":"Thégra","ecole_elementaire":1,"ecole_maternelle":1,"coordonnees":["1.7549677653024123","44.82474451160906"],"voie_generale":"","voie_technologique":"","voie_professionnelle":"","telephone":"565101470","web":"","mail":"ce.0460363V@ac-toulouse.fr","hebergement":"0","ulis":"0","lycee_des_metiers":"","apprentissage":"","segpa":"","section_arts":"","section_cinema":"","section_theatre":"","section_sport":"","section_internationale":"","section_europeenne":"","lycee_Agricole":"","lycee_militaire":"","nombre_d_eleves":"38","SIREN_SIRET":"21460317700020","date_ouverture":"1969-01-13","date_maj_ligne":"2019-09-11"}}]